portfolio/__init__.py
portfolio/portfolio_report.py
tests/__init__.py
tests/conftest.py
tests/test_io.py
Portfolio_Report_Generator-0.0.1.dist-info/LICENSE
Portfolio_Report_Generator-0.0.1.dist-info/METADATA
Portfolio_Report_Generator-0.0.1.dist-info/WHEEL
Portfolio_Report_Generator-0.0.1.dist-info/top_level.txt
Portfolio_Report_Generator-0.0.1.dist-info/RECORD
