Metadata-Version: 2.1
Name: Portfolio-Report-Generator
Version: 0.0.1
Summary: Generate report for a given stock portfolio.
Home-page: https://github.com/chandanrpai/assignment-7-chandanrpai
Author: Chandan Pai
Author-email: chandanrpai@gmail.com
License: UNKNOWN
Platform: UNKNOWN
Classifier: Programming Language :: Python :: 3
Classifier: License :: OSI Approved :: MIT License
Classifier: Operating System :: OS Independent
Requires-Python: >=3.6
